{
  "query_id": "04d4a224347e153590788e45c15d3ff0",
  "query_type": "normal",
  "method": "simmia",
  "model": "llama-3.3-70b-versatile",
  "backend": "groq",
  "sample_id": "BT_0198",
  "book_id": "The_Wildest_Sun_A_Novel_-_Asha_Lemmie",
  "label": 0,
  "length": "medium",
  "position": 7,
  "prefix": "We dance all night, stopping only for",
  "target_word": "me",
  "sample_idx": 1,
  "generated_text": "refreshments",
  "generated_first_word": "refreshments",
  "similarity": 0.5621896982192993,
  "timestamp": "2026-07-08 02:43:10"
}