{
  "query_id": "17c4f3a0e7dabc5f3b00ab7ed6775784",
  "method": "simmia",
  "model": "llama-3.3-70b-versatile",
  "backend": "groq",
  "sample_id": "BT_0048",
  "book_id": "Hedge_-_Jane_Delury",
  "label": 0,
  "length": "medium",
  "position": 18,
  "prefix": "Were going to take you to the hospital to get you checked out. I dont want to. We",
  "target_word": "need",
  "sample_idx": 2,
  "generated_text": "need",
  "generated_first_word": "need",
  "similarity": 1.0,
  "timestamp": "2026-06-27 01:06:28"
}