{
  "query_id": "256f3aea6868bd750b6889d6e12056e9",
  "method": "simmia",
  "model": "llama-3.3-70b-versatile",
  "backend": "groq",
  "sample_id": "BT_0045",
  "book_id": "What_Lies_in_the_Woods_-_Kate_Alice_Marshall",
  "label": 0,
  "length": "medium",
  "position": 11,
  "prefix": "A decade younger than I was now. Had Stahl offered her",
  "target_word": "a",
  "sample_idx": 0,
  "generated_text": "a",
  "generated_first_word": "a",
  "similarity": 1.0,
  "timestamp": "2026-06-27 00:58:49"
}