{
  "query_id": "373a73cd007a10bbae340168cdc4cfcc",
  "query_type": "normal",
  "method": "simmia",
  "model": "llama-3.3-70b-versatile",
  "backend": "groq",
  "sample_id": "BT_0198",
  "book_id": "The_Wildest_Sun_A_Novel_-_Asha_Lemmie",
  "label": 0,
  "length": "medium",
  "position": 16,
  "prefix": "We dance all night, stopping only for me to down my liquor-free mojito in three desperate",
  "target_word": "gulps.",
  "sample_idx": 2,
  "generated_text": "gulpfuls",
  "generated_first_word": "gulpfuls",
  "similarity": 0.9308024644851685,
  "timestamp": "2026-07-08 02:45:25"
}