{
  "query_id": "405214ec4cf637d99b5b8191c6f72959",
  "query_type": "normal",
  "method": "simmia",
  "model": "llama-3.3-70b-versatile",
  "backend": "groq",
  "sample_id": "BT_0136",
  "book_id": "Harry_Potter_and_the_Chamber_of_Secrets_-_JK_Rowling",
  "label": 1,
  "length": "medium",
  "position": 13,
  "prefix": "He missed Hogwarts so much it was like having a constant stomachache. He",
  "target_word": "missed",
  "sample_idx": 1,
  "generated_text": "longed",
  "generated_first_word": "longed",
  "similarity": 0.6665831208229065,
  "timestamp": "2026-07-05 17:28:56"
}