{
  "query_id": "43c8f01f2b3e25b4cce0a5f95acb6f40",
  "method": "simmia",
  "model": "llama-3.3-70b-versatile",
  "backend": "groq",
  "sample_id": "BT_0196",
  "book_id": "The_Alchemist_-_Paulo_Coelho",
  "label": 1,
  "length": "medium",
  "position": 12,
  "prefix": "The boy continued to listen to his heart as they crossed the",
  "target_word": "desert.",
  "sample_idx": 1,
  "generated_text": "bridge",
  "generated_first_word": "bridge",
  "similarity": 0.6130353808403015,
  "timestamp": "2026-06-27 19:56:15"
}