{
  "query_id": "46a58134b403e5c9f47a9d410feb2eff",
  "method": "simmia",
  "model": "llama-3.3-70b-versatile",
  "backend": "groq",
  "sample_id": "BT_0155",
  "book_id": "The_Silmarillion_-_J._R._R._Tolkien",
  "label": 1,
  "length": "medium",
  "position": 13,
  "prefix": "And this inner land, which was long named Eglador, was after called Doriath,",
  "target_word": "the",
  "sample_idx": 2,
  "generated_text": "the Realm",
  "generated_first_word": "the",
  "similarity": 1.0,
  "timestamp": "2026-06-27 18:26:17"
}