{
  "query_id": "4739d83a3b984536254a2ffa460b9f05",
  "method": "simmia",
  "model": "llama-3.3-70b-versatile",
  "backend": "groq",
  "sample_id": "BT_0077",
  "book_id": "The_Spectacular_-_Fiona_Davis",
  "label": 0,
  "length": "medium",
  "position": 16,
  "prefix": "Hornsby. He said to be ready when the car comes at eleven. Let me know if",
  "target_word": "you",
  "sample_idx": 1,
  "generated_text": "you're",
  "generated_first_word": "you're",
  "similarity": 0.8076314330101013,
  "timestamp": "2026-06-27 02:48:32"
}