{
  "query_id": "571cfb1c6e522cbaedb871e3aade4cfc",
  "query_type": "normal",
  "method": "simmia",
  "model": "llama-3.3-70b-versatile",
  "backend": "groq",
  "sample_id": "BT_0096",
  "book_id": "Unfortunately_Yours_-_Tessa_Bailey",
  "label": 0,
  "length": "medium",
  "position": 19,
  "prefix": "Hallie whooped and held up a glass of wine. I know thats right. Your turn, August, Julian prompted. Was",
  "target_word": "he",
  "sample_idx": 1,
  "generated_text": "it",
  "generated_first_word": "it",
  "similarity": 0.7859602570533752,
  "timestamp": "2026-07-04 19:13:36"
}