{
  "query_id": "5af24d3dfc713a10dfb7bb12175d9505",
  "query_type": "normal",
  "method": "simmia",
  "model": "llama-3.3-70b-versatile",
  "backend": "groq",
  "sample_id": "BT_0184",
  "book_id": "Unfortunately_Yours_-_Tessa_Bailey",
  "label": 0,
  "length": "medium",
  "position": 18,
  "prefix": "As for you? Marrying and employing a Vos will help you secure a small business loan. She threw",
  "target_word": "an",
  "sample_idx": 0,
  "generated_text": "the papers",
  "generated_first_word": "the",
  "similarity": 0.7978888154029846,
  "timestamp": "2026-07-08 01:41:34"
}