{
  "query_id": "5dd6d668535cdc3d5fbec72cdc3bf4c6",
  "method": "simmia",
  "model": "llama-3.3-70b-versatile",
  "backend": "groq",
  "sample_id": "BT_0053",
  "book_id": "The_Foxglove_King_-_Hannah_Whitten",
  "label": 0,
  "length": "medium",
  "position": 8,
  "prefix": "We talked about this. You talked about this.",
  "target_word": "Bastian",
  "sample_idx": 2,
  "generated_text": "before.",
  "generated_first_word": "before.",
  "similarity": 0.5808875560760498,
  "timestamp": "2026-06-27 01:50:33"
}