{
  "query_id": "630c28875c4eb05bb28317256103f501",
  "query_type": "normal",
  "method": "simmia",
  "model": "llama-3.3-70b-versatile",
  "backend": "groq",
  "sample_id": "BT_0022",
  "book_id": "Hedge_-_Jane_Delury",
  "label": 0,
  "length": "medium",
  "position": 19,
  "prefix": "I can come back tomorrow, she said. Lets stick to Wednesdays, Alice said. The following week, Maud worked faster",
  "target_word": "and",
  "sample_idx": 0,
  "generated_text": "and",
  "generated_first_word": "and",
  "similarity": 1.0,
  "timestamp": "2026-07-01 15:23:50"
}