{
  "query_id": "6d3b8ab1b389685023a592d502d56a7c",
  "query_type": "normal",
  "method": "simmia",
  "model": "llama-3.3-70b-versatile",
  "backend": "groq",
  "sample_id": "BT_0070",
  "book_id": "The_Silmarillion_-_J._R._R._Tolkien",
  "label": 1,
  "length": "medium",
  "position": 12,
  "prefix": "In this way he got his name, Bor, whereas his name before",
  "target_word": "had",
  "sample_idx": 2,
  "generated_text": "was",
  "generated_first_word": "was",
  "similarity": 0.7475413680076599,
  "timestamp": "2026-07-03 15:44:38"
}