{
  "query_id": "6dc9e316dc56ada7f01066497ecede3f",
  "query_type": "normal",
  "method": "simmia",
  "model": "llama-3.3-70b-versatile",
  "backend": "groq",
  "sample_id": "BT_0028",
  "book_id": "The_Foxglove_King_-_Hannah_Whitten",
  "label": 0,
  "length": "medium",
  "position": 10,
  "prefix": "Theres no need to go excavating ancient history. Though Alies",
  "target_word": "blush",
  "sample_idx": 2,
  "generated_text": "had",
  "generated_first_word": "had",
  "similarity": 0.6175185441970825,
  "timestamp": "2026-07-01 15:49:59"
}