{
  "query_id": "702458b8b7da95aac9ce4a224a682c8b",
  "method": "simmia",
  "model": "llama-3.3-70b-versatile",
  "backend": "groq",
  "sample_id": "BT_0059",
  "book_id": "1984_-_George_Orwell",
  "label": 1,
  "length": "medium",
  "position": 16,
  "prefix": "But the physical difficulty of meeting was enormous. It was like trying to make a move",
  "target_word": "at",
  "sample_idx": 0,
  "generated_text": "on",
  "generated_first_word": "on",
  "similarity": 0.7666929960250854,
  "timestamp": "2026-06-27 02:04:56"
}