{
  "query_id": "7345be7c420f13a271eef40e4bde6208",
  "query_type": "normal",
  "method": "simmia",
  "model": "llama-3.3-70b-versatile",
  "backend": "groq",
  "sample_id": "BT_0108",
  "book_id": "Business_or_Pleasure_-_Rachel_Lynn_Solomon",
  "label": 0,
  "length": "medium",
  "position": 3,
  "prefix": "Its the first",
  "target_word": "real",
  "sample_idx": 0,
  "generated_text": "day",
  "generated_first_word": "day",
  "similarity": 0.6390125155448914,
  "timestamp": "2026-07-04 20:04:49"
}