{
  "query_id": "87ad60d5467550f4952a76c9d4fc2017",
  "query_type": "normal",
  "method": "simmia",
  "model": "llama-3.3-70b-versatile",
  "backend": "groq",
  "sample_id": "BT_0190",
  "book_id": "The_Foxglove_King_-_Hannah_Whitten",
  "label": 0,
  "length": "medium",
  "position": 19,
  "prefix": "If Bastian knows who I am, Lore said, then why not just tell me? Or kill me? Isnt that",
  "target_word": "what",
  "sample_idx": 0,
  "generated_text": "what",
  "generated_first_word": "what",
  "similarity": 1.0,
  "timestamp": "2026-07-08 02:09:04"
}