{
  "query_id": "96797cd9208433bd3a0373297e27eacb",
  "method": "simmia",
  "model": "llama-3.3-70b-versatile",
  "backend": "groq",
  "sample_id": "BT_0026",
  "book_id": "Bartleby_the_Scrivener_A_Story_of_Wall_Street_-_Herman_Melville",
  "label": 1,
  "length": "medium",
  "position": 18,
  "prefix": "Go to the next room, and tell Nippers to come to me. I prefer not to, he respectfully",
  "target_word": "and",
  "sample_idx": 0,
  "generated_text": "declined,",
  "generated_first_word": "declined,",
  "similarity": 0.6208910346031189,
  "timestamp": "2026-06-26 23:51:55"
}