{
  "query_id": "b48098af0a661a818cbc0fda675d9f6d",
  "method": "simmia",
  "model": "llama-3.3-70b-versatile",
  "backend": "groq",
  "sample_id": "BT_0097",
  "book_id": "Harry_Potter_and_the_Chamber_of_Secrets_-_JK_Rowling",
  "label": 1,
  "length": "medium",
  "position": 18,
  "prefix": "“Er — Professor Lockhart?” Hermione stammered. “I wanted to — to get this book out of the library.",
  "target_word": "Just",
  "sample_idx": 0,
  "generated_text": "But\"",
  "generated_first_word": "But\"",
  "similarity": 0.6534407138824463,
  "timestamp": "2026-06-27 16:18:02"
}