{
  "query_id": "c2878633b65f0bb5013d437a61098dab",
  "method": "simmia",
  "model": "llama-3.3-70b-versatile",
  "backend": "groq",
  "sample_id": "BT_0141",
  "book_id": "The_Wildest_Sun_A_Novel_-_Asha_Lemmie",
  "label": 0,
  "length": "medium",
  "position": 14,
  "prefix": "I am of average height, but as gangly as someone much taller, with skinny",
  "target_word": "arms",
  "sample_idx": 2,
  "generated_text": "legs",
  "generated_first_word": "legs",
  "similarity": 0.7986250519752502,
  "timestamp": "2026-06-27 17:55:15"
}