{
  "query_id": "c76d73f67042fcc957c7be50ecb6b263",
  "query_type": "normal",
  "method": "simmia",
  "model": "llama-3.3-70b-versatile",
  "backend": "groq",
  "sample_id": "BT_0162",
  "book_id": "The_Darkness_Before_Them_-_Matthew_Ward",
  "label": 0,
  "length": "medium",
  "position": 8,
  "prefix": "Kat bunched her fists and fought the urge",
  "target_word": "to",
  "sample_idx": 0,
  "generated_text": "to",
  "generated_first_word": "to",
  "similarity": 1.0000001192092896,
  "timestamp": "2026-07-06 17:11:25"
}