{
  "query_id": "ce028f7d14087e5629f923fa2e4dd8a6",
  "query_type": "normal",
  "method": "simmia",
  "model": "llama-3.3-70b-versatile",
  "backend": "groq",
  "sample_id": "BT_0038",
  "book_id": "The_Darkness_Before_Them_-_Matthew_Ward",
  "label": 0,
  "length": "medium",
  "position": 10,
  "prefix": "But for all of that, it was a simple joy",
  "target_word": "to",
  "sample_idx": 0,
  "generated_text": "that",
  "generated_first_word": "that",
  "similarity": 0.6608291864395142,
  "timestamp": "2026-07-02 00:10:41"
}