{
  "query_id": "d04d40cfa22566fca40784fdda50817d",
  "method": "simmia",
  "model": "llama-3.3-70b-versatile",
  "backend": "groq",
  "sample_id": "BT_0001",
  "book_id": "The_Alchemist_-_Paulo_Coelho",
  "label": 1,
  "length": "medium",
  "position": 14,
  "prefix": "“And I know the Soul of the World, because we have talked at great",
  "target_word": "length",
  "sample_idx": 2,
  "generated_text": "lengths",
  "generated_first_word": "lengths",
  "similarity": 0.9710360765457153,
  "timestamp": "2026-06-26 22:45:02"
}