{
  "query_id": "d685b184b470d0f9a6035d82f5936f01",
  "query_type": "normal",
  "method": "simmia",
  "model": "llama-3.3-70b-versatile",
  "backend": "groq",
  "sample_id": "BT_0042",
  "book_id": "Oliver_Twist_-_Charles_Dickens",
  "label": 1,
  "length": "medium",
  "position": 5,
  "prefix": "Never mind how he came",
  "target_word": "there;",
  "sample_idx": 1,
  "generated_text": "to",
  "generated_first_word": "to",
  "similarity": 0.6315935850143433,
  "timestamp": "2026-07-02 00:28:19"
}