{
  "query_id": "e2aee2e4ae917c53300f7fcaba6d20ad",
  "method": "simmia",
  "model": "llama-3.3-70b-versatile",
  "backend": "groq",
  "sample_id": "BT_0039",
  "book_id": "Matilda_-_Roald_Dahl",
  "label": 1,
  "length": "medium",
  "position": 16,
  "prefix": "She settled herself and began to concentrate, and very quickly this time she felt the electricity",
  "target_word": "beginning",
  "sample_idx": 0,
  "generated_text": "coursing",
  "generated_first_word": "coursing",
  "similarity": 0.656488835811615,
  "timestamp": "2026-06-27 00:21:34"
}