{
  "query_id": "e4aef76ffd3a1da12c131bb772044eba",
  "query_type": "normal",
  "method": "simmia",
  "model": "llama-3.3-70b-versatile",
  "backend": "groq",
  "sample_id": "BT_0024",
  "book_id": "Wuthering_Heights_-_Emily_Bronte",
  "label": 1,
  "length": "medium",
  "position": 7,
  "prefix": "Side out o' t' gate now, this",
  "target_word": "minute!\"",
  "sample_idx": 1,
  "generated_text": "fellow's",
  "generated_first_word": "fellow's",
  "similarity": 0.6539089679718018,
  "timestamp": "2026-07-01 15:30:19"
}