{
  "query_id": "f23e711aaa0c888bbb87c4ff53c6dd15",
  "method": "simmia",
  "model": "llama-3.3-70b-versatile",
  "backend": "groq",
  "sample_id": "BT_0097",
  "book_id": "Harry_Potter_and_the_Chamber_of_Secrets_-_JK_Rowling",
  "label": 1,
  "length": "medium",
  "position": 7,
  "prefix": "“Er — Professor Lockhart?” Hermione stammered. “I",
  "target_word": "wanted",
  "sample_idx": 1,
  "generated_text": "was",
  "generated_first_word": "was",
  "similarity": 0.6764560341835022,
  "timestamp": "2026-06-27 16:16:48"
}