{
  "query_id": "f705786698095b1f273c72b77779d23b",
  "query_type": "normal",
  "method": "simmia",
  "model": "llama-3.3-70b-versatile",
  "backend": "groq",
  "sample_id": "BT_0025",
  "book_id": "Wuthering_Heights_-_Emily_Bronte",
  "label": 1,
  "length": "medium",
  "position": 15,
  "prefix": "Miss Cathy had been sick, and that made her still. She leant against her father's",
  "target_word": "knee,",
  "sample_idx": 1,
  "generated_text": "shoulder,",
  "generated_first_word": "shoulder,",
  "similarity": 0.7860979437828064,
  "timestamp": "2026-07-01 15:36:59"
}