{
  "query_id": "33635dca9ee77b678f80fdd351a2f7fe",
  "query_type": "normal",
  "method": "simmia",
  "model": "llama-3.1-8b-instant",
  "backend": "groq",
  "sample_id": "BT_0135",
  "book_id": "The_Spectacular_-_Fiona_Davis",
  "label": 0,
  "length": "medium",
  "position": 14,
  "prefix": "Not when Im finally finding my way in the world. I miss you. Her",
  "target_word": "eyes",
  "sample_idx": 0,
  "generated_text": "eyes",
  "generated_first_word": "eyes",
  "similarity": 1.0,
  "timestamp": "2026-06-30 16:23:05"
}