{
  "query_id": "371ca655431b56cf726c0c90117f8c35",
  "query_type": "normal",
  "method": "simmia",
  "model": "llama-3.1-8b-instant",
  "backend": "groq",
  "sample_id": "BT_0062",
  "book_id": "Oliver_Twist_-_Charles_Dickens",
  "label": 1,
  "length": "medium",
  "position": 15,
  "prefix": "So am I,' said the tinker, waking up, as suddenly as he had fallen asleep.",
  "target_word": "Brittles",
  "sample_idx": 0,
  "generated_text": "His eyes flutter",
  "generated_first_word": "His",
  "similarity": 0.5608677864074707,
  "timestamp": "2026-06-30 10:15:39"
}