{
  "query_id": "5cb77b0336c2a3435dd518aaad8cc9d1",
  "query_type": "normal",
  "method": "simmia",
  "model": "llama-3.1-8b-instant",
  "backend": "groq",
  "sample_id": "BT_0030",
  "book_id": "Harry_Potter_and_the_Chamber_of_Secrets_-_JK_Rowling",
  "label": 1,
  "length": "medium",
  "position": 14,
  "prefix": "He dreamed that he was on show in a zoo, with a card reading",
  "target_word": "UNDERAGE",
  "sample_idx": 2,
  "generated_text": "\"Wild Lion",
  "generated_first_word": "Wild",
  "similarity": 0.6268147826194763,
  "timestamp": "2026-06-30 07:26:34"
}