{
  "query_id": "7239eef98b2875923f3d3fbc1f34d325",
  "query_type": "normal",
  "method": "simmia",
  "model": "llama-3.1-8b-instant",
  "backend": "groq",
  "sample_id": "BT_0034",
  "book_id": "Unfortunately_Yours_-_Tessa_Bailey",
  "label": 0,
  "length": "medium",
  "position": 5,
  "prefix": "Well, hes a lot more",
  "target_word": "selfless",
  "sample_idx": 0,
  "generated_text": "confident.",
  "generated_first_word": "confident.",
  "similarity": 0.6473264694213867,
  "timestamp": "2026-06-30 07:43:42"
}