{
  "query_id": "90980ba2969cda69e7793831bec9bdac",
  "query_type": "normal",
  "method": "simmia",
  "model": "llama-3.1-8b-instant",
  "backend": "groq",
  "sample_id": "BT_0161",
  "book_id": "The_Spectacular_-_Fiona_Davis",
  "label": 0,
  "length": "medium",
  "position": 16,
  "prefix": "But his personality changed drastically. Where he once was an even-keeled, decent man, after his recovery",
  "target_word": "he",
  "sample_idx": 1,
  "generated_text": "he became mo",
  "generated_first_word": "he",
  "similarity": 1.0,
  "timestamp": "2026-07-01 01:35:16"
}