{
  "query_id": "91c2f445c7fac34c6a10ac01ed4bc89c",
  "query_type": "normal",
  "method": "simmia",
  "model": "llama-3.1-8b-instant",
  "backend": "groq",
  "sample_id": "BT_0069",
  "book_id": "The_Spectacular_-_Fiona_Davis",
  "label": 0,
  "length": "medium",
  "position": 4,
  "prefix": "But when one of",
  "target_word": "Marions",
  "sample_idx": 1,
  "generated_text": "those individuals",
  "generated_first_word": "those",
  "similarity": 0.6473274230957031,
  "timestamp": "2026-06-30 10:49:15"
}