{
  "query_id": "a371867dbcfb0079127c1201439e09ea",
  "query_type": "normal",
  "method": "simmia",
  "model": "llama-3.1-8b-instant",
  "backend": "groq",
  "sample_id": "BT_0163",
  "book_id": "Happy_Place_-_Emily_Henry",
  "label": 0,
  "length": "medium",
  "position": 13,
  "prefix": "A happiness so bright and hot you feel like it could incinerate you.",
  "target_word": "That",
  "sample_idx": 2,
  "generated_text": "It's almost",
  "generated_first_word": "It's",
  "similarity": 0.686504602432251,
  "timestamp": "2026-07-01 01:44:34"
}