{
  "query_id": "ad06fd3289f62e7e0f069237bd268d7e",
  "query_type": "normal",
  "method": "simmia",
  "model": "llama-3.1-8b-instant",
  "backend": "groq",
  "sample_id": "BT_0102",
  "book_id": "Hedge_-_Jane_Delury",
  "label": 0,
  "length": "medium",
  "position": 14,
  "prefix": "Maud smiled as she passed the pond again. Neither Frazer nor Chris had said",
  "target_word": "anything",
  "sample_idx": 1,
  "generated_text": "anything about her",
  "generated_first_word": "anything",
  "similarity": 1.0000001192092896,
  "timestamp": "2026-06-30 13:39:58"
}