{
  "query_id": "b4afd4f4a7323fdf43a744d14bfb4752",
  "query_type": "normal",
  "method": "simmia",
  "model": "llama-3.1-8b-instant",
  "backend": "groq",
  "sample_id": "BT_0044",
  "book_id": "The_Foxglove_King_-_Hannah_Whitten",
  "label": 0,
  "length": "medium",
  "position": 18,
  "prefix": "Lore scowled at his back, gathering her hem high to avoid the water. Hes just as caught up",
  "target_word": "in",
  "sample_idx": 2,
  "generated_text": "in the chaos",
  "generated_first_word": "in",
  "similarity": 1.0,
  "timestamp": "2026-06-30 08:40:54"
}