{
  "query_id": "c2f7ea247b53a5180a85a4f6dcb77565",
  "query_type": "normal",
  "method": "simmia",
  "model": "llama-3.1-8b-instant",
  "backend": "groq",
  "sample_id": "BT_0033",
  "book_id": "Matilda_-_Roald_Dahl",
  "label": 1,
  "length": "medium",
  "position": 10,
  "prefix": "There was a muddy pond at the bottom of Lavender’s",
  "target_word": "garden",
  "sample_idx": 2,
  "generated_text": "garden,",
  "generated_first_word": "garden,",
  "similarity": 0.9776903986930847,
  "timestamp": "2026-06-30 07:40:00"
}