{
  "query_id": "c437cdfa81ff8948965d6c0f7adbe8fe",
  "query_type": "normal",
  "method": "simmia",
  "model": "llama-3.1-8b-instant",
  "backend": "groq",
  "sample_id": "BT_0115",
  "book_id": "The_Foxglove_King_-_Hannah_Whitten",
  "label": 0,
  "length": "medium",
  "position": 10,
  "prefix": "If I were someone who partook in such things, it",
  "target_word": "would",
  "sample_idx": 2,
  "generated_text": "would",
  "generated_first_word": "would",
  "similarity": 0.9999999403953552,
  "timestamp": "2026-06-30 14:43:14"
}