{
  "query_id": "f7dfc55550f4d8624d679f997884c942",
  "query_type": "normal",
  "method": "simmia",
  "model": "llama-3.1-8b-instant",
  "backend": "groq",
  "sample_id": "BT_0157",
  "book_id": "The_Spectacular_-_Fiona_Davis",
  "label": 0,
  "length": "medium",
  "position": 6,
  "prefix": "Who knows what the future holds,",
  "target_word": "right?",
  "sample_idx": 0,
  "generated_text": "full of mysteries",
  "generated_first_word": "full",
  "similarity": 0.613571286201477,
  "timestamp": "2026-06-30 18:39:09"
}