{
  "query_id": "f916e9c7e9e7eef58931601b876752a3",
  "query_type": "normal",
  "method": "simmia",
  "model": "llama-3.1-8b-instant",
  "backend": "groq",
  "sample_id": "BT_0192",
  "book_id": "The_Age_of_Innocence_-_Edith_Wharton",
  "label": 1,
  "length": "medium",
  "position": 10,
  "prefix": "\"Call it what you like: you look at things as",
  "target_word": "they",
  "sample_idx": 1,
  "generated_text": "they are.",
  "generated_first_word": "they",
  "similarity": 1.0,
  "timestamp": "2026-07-01 04:10:36"
}