{
  "query_id": "f977b786283af7800c122678844340c5",
  "query_type": "normal",
  "method": "simmia",
  "model": "llama-3.1-8b-instant",
  "backend": "groq",
  "sample_id": "BT_0151",
  "book_id": "Happy_Place_-_Emily_Henry",
  "label": 0,
  "length": "medium",
  "position": 12,
  "prefix": "Then I plop it onto the wheel and flatten it with the",
  "target_word": "heels",
  "sample_idx": 0,
  "generated_text": "edge of the",
  "generated_first_word": "edge",
  "similarity": 0.6894236207008362,
  "timestamp": "2026-06-30 18:10:51"
}